allofplos/__init__.py
allofplos/article.py
allofplos/citation_utilities.py
allofplos/dbtoorm.py
allofplos/jupyter_nbconvert_config.py
allofplos/makedb.py
allofplos/plos_regex.py
allofplos/starter_data.py
allofplos/transformations.py
allofplos/update.py
allofplos/utils.py
allofplos/corpus/__init__.py
allofplos/corpus/corpus.py
allofplos/corpus/plos_corpus.py
allofplos/elements/__init__.py
allofplos/elements/article_elements.py
allofplos/elements/journal.py
allofplos/elements/license.py
allofplos/samples/__init__.py
allofplos/samples/corpus_analysis.py
allofplos/starter_corpus/__init__.py
allofplos-1.1.1.dist-info/licenses/LICENSE
allofplos-1.1.1.dist-info/METADATA
allofplos-1.1.1.dist-info/WHEEL
allofplos-1.1.1.dist-info/top_level.txt
allofplos-1.1.1.dist-info/RECORD
