Metadata-Version: 2.4
Name: allofplos
Version: 1.1.1
Summary: Get and analyze all PLOS articles
Author-email: Elizabeth Seiver <eseiver@plos.org>, Sebastian Bassi <sebastian.bassi@globant.com>, M Pacer <mpacer@berkeley.edu>
Maintainer-email: Erik Hetzner <ehetzner@plos.org>, Kevin Brandt <kbrandt@plos.org>
License: MIT License
Keywords: science,PLOS,publishing,PLoS
Classifier: Development Status :: 5 - Production/Stable
Classifier: Intended Audience :: Science/Research
Classifier: Topic :: Scientific/Engineering
Classifier: License :: OSI Approved :: MIT License
Classifier: Programming Language :: Python :: 3.8
License-File: LICENSE
Requires-Dist: certifi
Requires-Dist: chardet
Requires-Dist: charset-normalizer
Requires-Dist: idna
Requires-Dist: lxml
Requires-Dist: peewee
Requires-Dist: pqdm
Requires-Dist: python-utils
Requires-Dist: requests
Requires-Dist: six
Requires-Dist: tqdm
Requires-Dist: unidecode
Requires-Dist: urllib3
Dynamic: license-file
